djangodaylessdate/__init__.py
djangodaylessdate/apps.py
djangodaylessdate/filters.py
djangodaylessdate/forms.py
djangodaylessdate/helpers.py
djangodaylessdate/models.py
djangodaylessdate/templates/djangodaylessdate/daylessdate_filter.html
django_daylessdate-1.1.dist-info/LICENSE
django_daylessdate-1.1.dist-info/METADATA
django_daylessdate-1.1.dist-info/WHEEL
django_daylessdate-1.1.dist-info/top_level.txt
django_daylessdate-1.1.dist-info/RECORD
